autochomsky/__init__.py
autochomsky-1.0.4.dist-info/LICENSE.txt
autochomsky-1.0.4.dist-info/METADATA
autochomsky-1.0.4.dist-info/WHEEL
autochomsky-1.0.4.dist-info/top_level.txt
autochomsky-1.0.4.dist-info/RECORD
