Metadata-Version: 2.1
Name: autochomsky
Version: 1.0.4
Summary: Chomsky phrase generator
Home-page: https://github.com/gregfitch/autochomsky
Author: OpenStax QA
Author-email: greg@openstax.org
License: Creative Commons Attribution 4.0 International Public License
Platform: UNKNOWN
Requires-Dist: atomicwrites (==1.2.1)
Requires-Dist: attrs (==18.2.0)
Requires-Dist: coverage (==4.5.2)
Requires-Dist: more-itertools (==4.3.0)
Requires-Dist: pluggy (==0.8.0)
Requires-Dist: py (==1.7.0)
Requires-Dist: pytest (==4.0.2)
Requires-Dist: pytest-cov (==2.6.0)
Requires-Dist: six (==1.12.0)
